QC23006UNO/__init__.py
QC23006UNO/metodos.py
qc23006uno-0.2.0.dist-info/licenses/LICENSE
qc23006uno-0.2.0.dist-info/METADATA
qc23006uno-0.2.0.dist-info/WHEEL
qc23006uno-0.2.0.dist-info/top_level.txt
qc23006uno-0.2.0.dist-info/RECORD
