Metadata-Version: 2.4
Name: QC23006UNO
Version: 0.2.0
Summary: Librería de sistemas de ecuaciones lineales y no lineales
Home-page: https://github.com/tuusuario/GG14054UNO
Author: Alexandra Quinteros
Author-email: Alexandra Quinteros <QC23006@ues.edu.sv>
License: MIT
Requires-Python: >=3.6
License-File: LICENSE
Requires-Dist: numpy
Dynamic: author
Dynamic: home-page
Dynamic: license-file
Dynamic: requires-python
